<annotation>
	<folder>temp2</folder>
	<filename>1534483416.94.jpg</filename>
	<path>D:\studyINF\AI\YOLOv3\yolo_img3\temp2\1534483416.94.jpg</path>
	<source>
		<database>Unknown</database>
	</source>
	<size>
		<width>416</width>
		<height>416</height>
		<depth>3</depth>
	</size>
	<segmented>0</segmented>
	<object>
		<name>chess</name>
		<pose>Unspecified</pose>
		<truncated>0</truncated>
		<difficult>0</difficult>
		<bndbox>
			<xmin>299</xmin>
			<ymin>183</ymin>
			<xmax>316</xmax>
			<ymax>195</ymax>
		</bndbox>
	</object>
	<object>
		<name>chess</name>
		<pose>Unspecified</pose>
		<truncated>0</truncated>
		<difficult>0</difficult>
		<bndbox>
			<xmin>213</xmin>
			<ymin>223</ymin>
			<xmax>229</xmax>
			<ymax>234</ymax>
		</bndbox>
	</object>
	<object>
		<name>ball</name>
		<pose>Unspecified</pose>
		<truncated>0</truncated>
		<difficult>0</difficult>
		<bndbox>
			<xmin>277</xmin>
			<ymin>195</ymin>
			<xmax>296</xmax>
			<ymax>219</ymax>
		</bndbox>
	</object>
	<object>
		<name>ball</name>
		<pose>Unspecified</pose>
		<truncated>0</truncated>
		<difficult>0</difficult>
		<bndbox>
			<xmin>125</xmin>
			<ymin>160</ymin>
			<xmax>142</xmax>
			<ymax>178</ymax>
		</bndbox>
	</object>
	<object>
		<name>ball</name>
		<pose>Unspecified</pose>
		<truncated>0</truncated>
		<difficult>0</difficult>
		<bndbox>
			<xmin>36</xmin>
			<ymin>212</ymin>
			<xmax>61</xmax>
			<ymax>237</ymax>
		</bndbox>
	</object>
	<object>
		<name>pen</name>
		<pose>Unspecified</pose>
		<truncated>0</truncated>
		<difficult>0</difficult>
		<bndbox>
			<xmin>203</xmin>
			<ymin>169</ymin>
			<xmax>239</xmax>
			<ymax>179</ymax>
		</bndbox>
	</object>
	<object>
		<name>pen</name>
		<pose>Unspecified</pose>
		<truncated>0</truncated>
		<difficult>0</difficult>
		<bndbox>
			<xmin>330</xmin>
			<ymin>281</ymin>
			<xmax>355</xmax>
			<ymax>334</ymax>
		</bndbox>
	</object>
	<object>
		<name>pen</name>
		<pose>Unspecified</pose>
		<truncated>0</truncated>
		<difficult>0</difficult>
		<bndbox>
			<xmin>65</xmin>
			<ymin>289</ymin>
			<xmax>120</xmax>
			<ymax>305</ymax>
		</bndbox>
	</object>
	<object>
		<name>ball</name>
		<pose>Unspecified</pose>
		<truncated>0</truncated>
		<difficult>0</difficult>
		<bndbox>
			<xmin>177</xmin>
			<ymin>284</ymin>
			<xmax>203</xmax>
			<ymax>317</ymax>
		</bndbox>
	</object>
</annotation>
